niwa_api/__init__.py
niwa_api/cli.py
niwa_api/tideclient.py
niwa_api_client-0.1.6.dist-info/METADATA
niwa_api_client-0.1.6.dist-info/WHEEL
niwa_api_client-0.1.6.dist-info/entry_points.txt
niwa_api_client-0.1.6.dist-info/top_level.txt
niwa_api_client-0.1.6.dist-info/RECORD
