Metadata-Version: 2.1
Name: niwa-api-client
Version: 0.1.6
Summary: Client for NIWA's APIs
Requires-Python: >=3.12
Requires-Dist: httpx >=0.27.2
Requires-Dist: typer >=0.12.5
